{
  "minecraft:recipes/building_blocks/stone_bricks": {
    "criteria": {
      "has_stone": "2026-05-24 15:27:05 +0200"
    },
    "done": true
  },
  "minecraft:recipes/decorations/prismarine_wall_from_prismarine_stonecutting": {
    "criteria": {
      "has_prismarine": "2026-05-24 15:27:05 +0200"
    },
    "done": true
  },
  "minecraft:recipes/building_blocks/chiseled_stone_bricks_from_stone_stonecutting": {
    "criteria": {
      "has_stone": "2026-05-24 15:27:05 +0200"
    },
    "done": true
  },
  "minecraft:recipes/building_blocks/stone_bricks_from_stone_stonecutting": {
    "criteria": {
      "has_stone": "2026-05-24 15:27:05 +0200"
    },
    "done": true
  },
  "minecraft:recipes/building_blocks/stone_slab": {
    "criteria": {
      "has_stone": "2026-05-24 15:27:05 +0200"
    },
    "done": true
  },
  "minecraft:recipes/decorations/composter": {
    "criteria": {
      "has_wood_slab": "2026-05-24 15:27:05 +0200"
    },
    "done": true
  },
  "minecraft:recipes/decorations/crafting_table": {
    "criteria": {
      "unlock_right_away": "2026-05-24 15:27:05 +0200"
    },
    "done": true
  },
  "minecraft:recipes/decorations/chest": {
    "criteria": {
      "has_lots_of_items": "2026-05-24 15:27:05 +0200"
    },
    "done": true
  },
  "minecraft:recipes/decorations/prismarine_wall": {
    "criteria": {
      "has_prismarine": "2026-05-24 15:27:05 +0200"
    },
    "done": true
  },
  "minecraft:recipes/building_blocks/stone_stairs_from_stone_stonecutting": {
    "criteria": {
      "has_stone": "2026-05-24 15:27:05 +0200"
    },
    "done": true
  },
  "minecraft:recipes/building_blocks/prismarine_slab_from_prismarine_stonecutting": {
    "criteria": {
      "has_prismarine": "2026-05-24 15:27:05 +0200"
    },
    "done": true
  },
  "minecraft:recipes/building_blocks/spruce_wood": {
    "criteria": {
      "has_log": "2026-05-24 15:27:05 +0200"
    },
    "done": true
  },
  "minecraft:recipes/decorations/stone_brick_wall_from_stone_stonecutting": {
    "criteria": {
      "has_stone": "2026-05-24 15:27:05 +0200"
    },
    "done": true
  },
  "minecraft:recipes/decorations/cobblestone_wall_from_stone_stonecutting": {
    "criteria": {
      "has_stone": "2026-05-24 15:27:05 +0200"
    },
    "done": true
  },
  "minecraft:recipes/redstone/stone_button": {
    "criteria": {
      "has_stone": "2026-05-24 15:27:05 +0200"
    },
    "done": true
  },
  "minecraft:recipes/decorations/stonecutter": {
    "criteria": {
      "has_stone": "2026-05-24 15:27:05 +0200"
    },
    "done": true
  },
  "minecraft:recipes/redstone/stone_pressure_plate": {
    "criteria": {
      "has_stone": "2026-05-24 15:27:05 +0200"
    },
    "done": true
  },
  "minecraft:recipes/building_blocks/smooth_stone": {
    "criteria": {
      "has_stone": "2026-05-24 15:27:05 +0200"
    },
    "done": true
  },
  "minecraft:recipes/building_blocks/cobblestone_slab_from_stone_stonecutting": {
    "criteria": {
      "has_stone": "2026-05-24 15:27:05 +0200"
    },
    "done": true
  },
  "minecraft:recipes/building_blocks/prismarine_stairs_from_prismarine_stonecutting": {
    "criteria": {
      "has_prismarine": "2026-05-24 15:27:05 +0200"
    },
    "done": true
  },
  "minecraft:recipes/building_blocks/stone_brick_slab_from_stone_stonecutting": {
    "criteria": {
      "has_stone": "2026-05-24 15:27:05 +0200"
    },
    "done": true
  },
  "minecraft:recipes/building_blocks/spruce_planks": {
    "criteria": {
      "has_logs": "2026-05-24 15:27:05 +0200"
    },
    "done": true
  },
  "minecraft:recipes/building_blocks/stone_brick_stairs_from_stone_stonecutting": {
    "criteria": {
      "has_stone": "2026-05-24 15:27:05 +0200"
    },
    "done": true
  },
  "minecraft:recipes/building_blocks/cobblestone_stairs_from_stone_stonecutting": {
    "criteria": {
      "has_stone": "2026-05-24 15:27:05 +0200"
    },
    "done": true
  },
  "minecraft:recipes/building_blocks/stone_slab_from_stone_stonecutting": {
    "criteria": {
      "has_stone": "2026-05-24 15:27:05 +0200"
    },
    "done": true
  },
  "minecraft:recipes/tools/flint_and_steel": {
    "criteria": {
      "has_obsidian": "2026-05-24 15:27:05 +0200"
    },
    "done": true
  },
  "minecraft:recipes/misc/charcoal": {
    "criteria": {
      "has_log": "2026-05-24 15:27:05 +0200"
    },
    "done": true
  },
  "minecraft:story/form_obsidian": {
    "criteria": {
      "obsidian": "2026-05-24 15:27:05 +0200"
    },
    "done": true
  },
  "minecraft:recipes/building_blocks/prismarine_stairs": {
    "criteria": {
      "has_prismarine": "2026-05-24 15:27:05 +0200"
    },
    "done": true
  },
  "minecraft:adventure/adventuring_time": {
    "criteria": {
      "minecraft:badlands": "2026-05-24 15:27:05 +0200",
      "minecraft:eroded_badlands": "2026-05-24 15:27:27 +0200"
    },
    "done": false
  },
  "minecraft:recipes/decorations/barrel": {
    "criteria": {
      "has_wood_slab": "2026-05-24 15:27:05 +0200"
    },
    "done": true
  },
  "minecraft:recipes/building_blocks/cobblestone_from_stone_stonecutting": {
    "criteria": {
      "has_stone": "2026-05-24 15:27:05 +0200"
    },
    "done": true
  },
  "minecraft:recipes/building_blocks/prismarine_slab": {
    "criteria": {
      "has_prismarine": "2026-05-24 15:27:05 +0200"
    },
    "done": true
  },
  "minecraft:recipes/decorations/enchanting_table": {
    "criteria": {
      "has_obsidian": "2026-05-24 15:27:05 +0200"
    },
    "done": true
  },
  "minecraft:recipes/building_blocks/stone_stairs": {
    "criteria": {
      "has_stone": "2026-05-24 15:27:05 +0200"
    },
    "done": true
  },
  "minecraft:story/obtain_armor": {
    "criteria": {
      "iron_helmet": "2026-05-24 15:28:15 +0200"
    },
    "done": true
  },
  "minecraft:recipes/misc/iron_nugget_from_smelting": {
    "criteria": {
      "has_iron_helmet": "2026-05-24 15:28:15 +0200"
    },
    "done": true
  },
  "minecraft:recipes/misc/iron_nugget_from_blasting": {
    "criteria": {
      "has_iron_helmet": "2026-05-24 15:28:15 +0200"
    },
    "done": true
  },
  "minecraft:recipes/decorations/lime_shulker_box": {
    "criteria": {
      "has_shulker_box": "2026-05-24 15:29:19 +0200"
    },
    "done": true
  },
  "minecraft:recipes/decorations/cyan_shulker_box": {
    "criteria": {
      "has_shulker_box": "2026-05-24 15:29:19 +0200"
    },
    "done": true
  },
  "minecraft:recipes/decorations/white_shulker_box": {
    "criteria": {
      "has_shulker_box": "2026-05-24 15:29:19 +0200"
    },
    "done": true
  },
  "minecraft:recipes/decorations/light_blue_shulker_box": {
    "criteria": {
      "has_shulker_box": "2026-05-24 15:29:19 +0200"
    },
    "done": true
  },
  "minecraft:recipes/decorations/magenta_shulker_box": {
    "criteria": {
      "has_shulker_box": "2026-05-24 15:29:19 +0200"
    },
    "done": true
  },
  "minecraft:recipes/decorations/light_gray_shulker_box": {
    "criteria": {
      "has_shulker_box": "2026-05-24 15:29:19 +0200"
    },
    "done": true
  },
  "minecraft:recipes/decorations/blue_shulker_box": {
    "criteria": {
      "has_shulker_box": "2026-05-24 15:29:19 +0200"
    },
    "done": true
  },
  "minecraft:recipes/decorations/orange_shulker_box": {
    "criteria": {
      "has_shulker_box": "2026-05-24 15:29:19 +0200"
    },
    "done": true
  },
  "minecraft:recipes/decorations/black_shulker_box": {
    "criteria": {
      "has_shulker_box": "2026-05-24 15:29:19 +0200"
    },
    "done": true
  },
  "minecraft:recipes/decorations/red_shulker_box": {
    "criteria": {
      "has_shulker_box": "2026-05-24 15:29:19 +0200"
    },
    "done": true
  },
  "minecraft:recipes/decorations/yellow_shulker_box": {
    "criteria": {
      "has_shulker_box": "2026-05-24 15:29:19 +0200"
    },
    "done": true
  },
  "minecraft:recipes/decorations/gray_shulker_box": {
    "criteria": {
      "has_shulker_box": "2026-05-24 15:29:19 +0200"
    },
    "done": true
  },
  "minecraft:recipes/decorations/purple_shulker_box": {
    "criteria": {
      "has_shulker_box": "2026-05-24 15:29:19 +0200"
    },
    "done": true
  },
  "minecraft:recipes/decorations/pink_shulker_box": {
    "criteria": {
      "has_shulker_box": "2026-05-24 15:29:19 +0200"
    },
    "done": true
  },
  "minecraft:recipes/decorations/green_shulker_box": {
    "criteria": {
      "has_shulker_box": "2026-05-24 15:29:19 +0200"
    },
    "done": true
  },
  "minecraft:recipes/building_blocks/dripstone_block": {
    "criteria": {
      "has_pointed_dripstone": "2026-05-24 15:28:59 +0200"
    },
    "done": true
  },
  "minecraft:recipes/decorations/brown_shulker_box": {
    "criteria": {
      "has_shulker_box": "2026-05-24 15:29:19 +0200"
    },
    "done": true
  },
  "DataVersion": 4790
}